<?xml version="1.0" encoding="utf-8"?>
<odoo>

    <record id="view_date_range_tree" model="ir.ui.view">
        <field name="name">date.range.view.tree.inherit</field>
        <field name="model">date.range</field>
        <field name="inherit_id" ref="date_range.view_date_range_tree" />
        <field name="arch" type="xml">
            <tree position="inside">
                <field name="product_template_ids" widget="many2many_tags"/>
            </tree>
        </field>
    </record>

</odoo>
