<?xml version="1.0" encoding="utf-8"?>
<odoo>

    <record id="product_product_view_tree" model="ir.ui.view">
        <field name="name">product.product.view.tree</field>
        <field name="model">product.product</field>
        <field name="arch" type="xml">
            <tree editable="top">
                <field name="default_code" optional="show" readonly="1"/>
                <field name="name" readonly="1"/>
                <field name="product_template_attribute_value_ids" widget="many2many_tags" groups="product.group_product_variant" readonly="1"/>
                <field name="company_id" groups="base.group_multi_company" optional="hide" readonly="1"/>
                <field name="lst_price" optional="show" string="Sales Price"/>
                <field name="date_range_id" />
                <field name="date_start" />
                <field name="date_end" />
                <field name="partner_id" />
            </tree>
        </field>
    </record>
    <record id="product_product_view_search" model="ir.ui.view">
        <field name="name">product.product.view.search</field>
        <field name="model">product.product</field>
        <field name="arch" type="xml">
            <search string="Product">
                <field name="name" filter_domain="['|', ('name','ilike',self), ('default_code','ilike',self)]" string="Name"/>
                <field name="date_start" filter_domain="[('date_start','=',self)]" string="Start Date"/>
                <field name="date_end" filter_domain="[('date_end','=',self)]" string="End Date"/>
                <searchpanel>
                    <field name="date_range_id"/>
                </searchpanel>
            </search>
        </field>
    </record>

    <!-- Action & Menuitem -->
    <record id="product_product_action" model="ir.actions.act_window">
        <field name="name">Packages</field>
        <field name="res_model">product.product</field>
        <field name="view_mode">tree,form</field>
        <field name="domain">[]</field>
        <field name="context">{}</field>
        <field name="view_id" ref="product_product_view_tree" />
        <field name="search_view_id" ref="product_product_view_search" />
    </record>
    <menuitem
        id="product_product_menu"
        name="Packages"
        action="product_product_action"
        parent="resource_booking.resource_booking_main_menu"
        sequence="5"
    />

</odoo>
